OpenShiftLibrary/__init__.py
OpenShiftLibrary/deprecated.py
OpenShiftLibrary/errors.py
OpenShiftLibrary/version.py
OpenShiftLibrary/client/__init__.py
OpenShiftLibrary/client/authapiclient.py
OpenShiftLibrary/client/authclient.py
OpenShiftLibrary/client/genericapiclient.py
OpenShiftLibrary/client/genericclient.py
OpenShiftLibrary/dataloader/__init__.py
OpenShiftLibrary/dataloader/dataloader.py
OpenShiftLibrary/dataloader/fileloader.py
OpenShiftLibrary/dataloader/urlloader.py
OpenShiftLibrary/dataparser/__init__.py
OpenShiftLibrary/dataparser/dataparser.py
OpenShiftLibrary/dataparser/jsonparser.py
OpenShiftLibrary/dataparser/yamlparser.py
OpenShiftLibrary/keywords/__init__.py
OpenShiftLibrary/keywords/events.py
OpenShiftLibrary/keywords/generic.py
OpenShiftLibrary/keywords/pods.py
OpenShiftLibrary/keywords/projects.py
OpenShiftLibrary/keywords/services.py
OpenShiftLibrary/outputformatter/__init__.py
OpenShiftLibrary/outputformatter/outputformatter.py
OpenShiftLibrary/outputformatter/plaintextformatter.py
OpenShiftLibrary/outputstreamer/__init__.py
OpenShiftLibrary/outputstreamer/logstreamer.py
OpenShiftLibrary/outputstreamer/outputstreamer.py
OpenShiftLibrary/templateloader/__init__.py
OpenShiftLibrary/templateloader/jinja2loader.py
OpenShiftLibrary/templateloader/templateloader.py
robotframework_openshift-1.0.0.dist-info/LICENSE
robotframework_openshift-1.0.0.dist-info/METADATA
robotframework_openshift-1.0.0.dist-info/WHEEL
robotframework_openshift-1.0.0.dist-info/top_level.txt
robotframework_openshift-1.0.0.dist-info/zip-safe
robotframework_openshift-1.0.0.dist-info/RECORD
