Metadata-Version: 2.1
Name: robotframework-openshift
Version: 1.0.0
Summary: Robotframework for OpenShift interactions
Home-page: https://github.com/red-hat-data-services/robotframework-openshift
Author: Pablo Félix Estévez Pico
Author-email: pestevez@redhat.com
License: Apache License 2.0
Keywords: robotframework openshift
Platform: any
License-File: LICENSE
Requires-Dist: reportportal-client
Requires-Dist: robotframework (>=4)
Requires-Dist: robotframework-debuglibrary
Requires-Dist: robotframework-seleniumlibrary
Requires-Dist: robotframework-jupyterlibrary (>=0.3.1)
Requires-Dist: ipython
Requires-Dist: openshift (==0.12.1)
Requires-Dist: pre-commit
Requires-Dist: pytest
Requires-Dist: pytest-logger
Requires-Dist: pyyaml
Requires-Dist: pygments
Requires-Dist: requests
Requires-Dist: Jinja2
Requires-Dist: flake8
Requires-Dist: mypy
Requires-Dist: kubernetes
Requires-Dist: validators
